artes/__init__.py
artes-0.0.1.dist-info/METADATA
artes-0.0.1.dist-info/WHEEL
artes-0.0.1.dist-info/top_level.txt
artes-0.0.1.dist-info/RECORD
