Metadata-Version: 2.1
Name: artes
Version: 0.0.1
Summary: Three-dimensional scattering radiative transfer for planetary atmospheres
Home-page: https://github.com/tomasstolker/ARTES
Author: Tomas Stolker
Author-email: tomas.stolker@phys.ethz.ch
License: GPLv3
Keywords: species
Platform: UNKNOWN
Classifier: Development Status :: 4 - Beta
Classifier: Intended Audience :: Science/Research
Classifier: Topic :: Scientific/Engineering :: Astronomy
Classifier: License :: OSI Approved :: GNU General Public License v3 (GPLv3)
Classifier: Natural Language :: English
Classifier: Programming Language :: Python :: 3.6
Classifier: Programming Language :: Python :: 3.7
Requires-Dist: numpy (~=1.18)
